g2pkiwi/__init__.py
g2pkiwi/__main__.py
g2pkiwi/__version__.py
g2pkiwi/english.py
g2pkiwi/g2pk.py
g2pkiwi/idioms.txt
g2pkiwi/numerals.py
g2pkiwi/regular.py
g2pkiwi/rules.txt
g2pkiwi/special.py
g2pkiwi/table.csv
g2pkiwi/utils.py
g2pkiwi-0.1.0.dist-info/entry_points.txt
g2pkiwi-0.1.0.dist-info/WHEEL
g2pkiwi-0.1.0.dist-info/METADATA
g2pkiwi-0.1.0.dist-info/licenses/LICENSE
g2pkiwi-0.1.0.dist-info/RECORD
