Metadata-Version: 2.1
Name: g2pkiwi
Version: 0.1.0
Summary: a fork of g2pK, using kiwipiepy; g2p module for Korean
License: Apache-2.0
Keywords: g2p,korean,g2pK,kiwipiepy
Author-email: dowon <ks2515@naver.com>
Requires-Python: >=3.7
Classifier: Intended Audience :: Developers
Classifier: Intended Audience :: Science/Research
Classifier: License :: OSI Approved :: Apache Software License
Classifier: Natural Language :: Korean
Classifier: Operating System :: OS Independent
Classifier: Programming Language :: Python :: 3
Classifier: Programming Language :: Python :: 3.10
Classifier: Programming Language :: Python :: 3.11
Classifier: Programming Language :: Python :: 3.7
Classifier: Programming Language :: Python :: 3.8
Classifier: Programming Language :: Python :: 3.9
Requires-Dist: jamo
Requires-Dist: kiwipiepy>=0.14.0
Requires-Dist: nltk
Project-URL: repository, https://github.com/Bing-su/g2pkiwi
